[{"date":"2014-06-18T17:19:30Z","author":"alex","fields":{"title":"Use release name as root directory in Gitblit GO artefacts","body":"Change the Gitblit artefacts to include a root directory that is the name of the release, E.g.\n\n    gitblit-X.Y.Z.tar.gz\n    |-- gitblit-X.Y.Z\n    |  |-- data\n    |  |-- docs\n    |  |-- ...","type":"Enhancement","mergeTo":"develop","watchers":"+alex","status":"New"}},{"date":"2014-06-19T08:03:50Z","author":"alex","patchset":{"number":1,"rev":1,"tip":"1e70e2b40e5a962154c54bb8004f923b51f1ddcb","base":"51241eadb22b08f01945fa9701eca5419ff38aa6","insertions":22,"deletions":17,"commits":1,"added":0,"type":"Proposal"}},{"date":"2014-07-01T03:04:33Z","author":"james","fields":{"watchers":"+james"},"patchset":{"number":1,"rev":2,"tip":"bba93c70ddc49fad6302c488393c1a4d517f2aa8","parent":"1e70e2b40e5a962154c54bb8004f923b51f1ddcb","base":"51241eadb22b08f01945fa9701eca5419ff38aa6","insertions":10,"deletions":10,"commits":2,"added":1,"type":"FastForward"}},{"date":"2014-07-01T03:05:45Z","author":"james","patchset":{"number":2,"rev":1,"tip":"184929de48ddcdb9724aed5f9a45d5834415aca9","base":"9b89bf102d1fb2cb96ce96eec746a594e539125c","insertions":24,"deletions":19,"commits":1,"added":0,"type":"Rebase_Squash"}}]